colemen_string_utils.py
facades/sql_convert_facade.py
facades/sql_generate_facade.py
facades/sql_parse_facade.py
utils/objectUtils.py
utils/parse_sql.py
utils/parse_utils.py
utils/sql_facade.py
utils/string_conversion.py
utils/string_format.py
utils/string_generation.py
colemen_string_utils-1.9.22.dist-info/METADATA
colemen_string_utils-1.9.22.dist-info/WHEEL
colemen_string_utils-1.9.22.dist-info/top_level.txt
colemen_string_utils-1.9.22.dist-info/RECORD
